<?xml version="1.0" encoding="utf-8"?>
<!--Generated by crowdin.com-->
<language>
	<display>Srpski</display>
	<resources>
		<!-- Font overrides - only change these if your language requires special characters -->
		<resource name="font_l" type="fontoverride" filename="RobotoCondensed-Regular.ttf" scale="90" />
		<resource name="font_m" type="fontoverride" filename="RobotoCondensed-Regular.ttf" scale="90" />
		<resource name="font_s" type="fontoverride" filename="RobotoCondensed-Regular.ttf" scale="90" />
		<resource name="fixed" type="fontoverride" filename="DroidSansMono.ttf" scale="100" />

		<string name="system">Sistem</string>
		<string name="system_image">Slika sistema</string>
		<string name="vendor">Proizvođač</string>
		<string name="vendor_image">Slika proizvođača</string>
		<string name="boot">But</string>
		<string name="recovery">Oporavak</string>
		<string name="cache">Keš</string>
		<string name="data">Podaci</string>
		<string name="sdcard">SD Kartica</string>
		<string name="internal">Unutrašnja kartica</string>
		<string name="microsd">Mikro SD kartica</string>
		<string name="usbotg">USB OTG</string>
		<string name="android_secure">Obezbeđenje Android</string>
		<string name="dalvik">Keš Dalvik/ART</string>
		<string name="sdext">SD-EXT II</string>
		<string name="adopted_data">Usvojeni podaci</string>
		<string name="adopted_storage">Usvojeno skladištenje podataka</string>
		<string name="twrp_header">Team Win Recovery Project</string>
		<string name="twrp_watch_header">TWRP %tw_version%</string>
		<string name="cpu_temp">Procesor: %tw_cpu_temp% °C</string>
		<string name="battery_pct">Baterija: %tw_battery%</string>
		<string name="sort_by_name">Razvrsti po imenu</string>
		<string name="sort_by_date">Razvrsti po datumu</string>
		<string name="sort_by_size">Razvrsti po velikosti</string>
		<string name="sort_by_name_only">Ime</string>
		<string name="sort_by_date_only">Datum</string>
		<string name="sort_by_size_only">Veličina</string>
		<string name="tab_general">OPŠTE</string>
		<string name="tab_options">OPCIJE</string>
		<string name="tab_backup">ČUVANJE</string>
		<string name="tab_time_zone">Vremenska zona</string>
		<string name="tab_screen">EKRAN</string>
		<string name="tab_vibration">VIBRACIJA</string>
		<string name="tab_language">JEZIK</string>
		<string name="install_btn">Instalacija</string>
		<string name="wipe_btn">Čistka</string>
		<string name="backup_btn">Čuvaj</string>
		<string name="restore_btn">Obnovi</string>
		<string name="mount_btn">Podigni</string>
		<string name="settings_btn">Podešavanje</string>
		<string name="advanced_btn">Napredno</string>
		<string name="reboot_btn">Reboot</string>
		<string name="files_btn">Datoteke</string>
		<string name="copy_log_btn">Kopiraj dnevnik</string>
		<string name="select_type_hdr">Izberite tip</string>
		<string name="install_zip_hdr">Instaliraj ZIP</string>
		<string name="install_zip_btn">Instaliraj ZIP</string>
		<string name="install_image_hdr">Instaliraj sliku</string>
		<string name="install_image_btn">Instaliraj sliku</string>
		<string name="install_select_file_hdr">Izberite datoteku</string>
		<string name="file_selector_folders_hdr">Putanja</string>
		<string name="select_file_from_storage">Izberite datoteku iz %tw_storage_display_name% (%tw_storage_free_size% MB)</string>
		<string name="adb_sideload_btn">SideLoad ADB</string>
		<string name="install_hdr">Instaliraj</string>
		<string name="select_storage_hdr">Izberite uređaj skladištenja</string>
		<string name="select_storage_btn">Izberite uređaj skladištenja</string>
		<string name="queue_hdr">Čeka u redu</string>
		<string name="zip_queue_count">%tw_zip_queue_count% od najviše 10 datoteka na čekanju</string>
		<string name="zip_queue_count_s">Datoteka %tw_zip_queue_count% od 10:</string>
<string name = "zip_varn1"> Ovaj zadatak se može instalirati incompatible </string>
<string name = "zip_varn2"> softver i čini uređaj beskorisnim. </string>
<string name = "zip_back_cancel"> Pritisnite Nazad da biste otkazali dodavanje ovog ZIP-a. </string>
<string name = "zip_back_clear"> Pritisnite Nazad da biste stavili red u red. </string>
<string name = "folder"> Folder: </string>
<string name = "file"> Datoteka: </string>
<string name = "zip_sig_chk"> Proveri ZIP potpis </string>
<string name = "inject_TWRP_chk"> Ubacite TWRP nakon instalacije </string>
<string name = "options_hdr"> Opcije </string>
<string name = "confirm_flash_hdr"> Potvrdi instalaciju </string>
<string name = "zip_kueue"> Tip čekanja: </string>
<string name = "options"> Opcije: </string>
<string name = "swipe_confirm"> Potvrdi </string>
<string name = "zip_add_btn"> Dodaj još ZIP-ova </string>
<string name = "zip_clear_btn"> Obrišite ZIP red </string>
<string name = "install_zip_count_hdr"> Instaliraj ZIP% tv_zip_indek% od% tv_zip_kueue_count% </string>
<string name = "installing_zip_kml"> Instaliranje ZIP-a:% tv_file% </string>
<string name = "failed"> Spodeled </string>
<string name = "successful"> Uspeh </string>
<string name = "install_failed"> Instalacija nije uspela </string>
<string name = "install_successful"> Instalacija je uspela </string>
<string name = "vipe_cache_dalvik_btn"> Obriši keš / Dalvik </string>
<string name = "reboot_sistem_btn"> Restart sistem </string>
<string name = "install_sel_target"> Izaberite ciljni odeljak </string>
<string name = "flash_image_select"> Izaberite odeljak za štampanje: </string>
<string name = "target_partition"> Odredište: </string>
<string name = "flashing_image"> Instaliranje otiska ... </string>
<string name = "image_flashed"> Print je instaliran </string>
<string name = "vipe_cache_dalvik_confirm"> Obriši keš i Dalvik? </string>
<string name = "viping_cache_dalvik"> Brisanje keša i Dalvik ... </string>
<string name = "vipe_cache_dalvik_complete"> Brisanje keš memorije i dovršeno </string>
<string name = "swipe_vipe"> Povucite za čišćenje </string>
<string name = "swipe_vipe_s"> Obriši </string>
<string name = "no_os1"> OS nije instaliran! Ili stvarno </string>
<string name = "no_osrb"> želite da restartujete? </string>
<string name = "no_ospo"> želite isključiti? </string>
<string name = "rebooting"> Ponovo pokreni ... </string>
<string name = "swipe_reboot"> Povucite da biste ponovo pokrenuli </string>
<string name = "swipe_reboot_s"> Ponovo pokreni </string>
<string name = "swipe_flash"> Povucite za potvrdu instalacije </string>
<string name = "confirm_action"> Potvrdi akciju </string>
<string name = "back_cancel"> Pritisnite Nazad da biste otkazali. </string>
<string name = "cancel_btn"> Otkaži </string>
<string name = "vipe_hdr"> Obriši </string>
<string name = "factori_reset_hdr"> Reset na neuspešno. </string>
<string name = "factori_reset_btn"> Reset na neuspešno. </string>
<string name = "factori_reset1"> Obriši podatke, keš i Dalvik </string>
<string name = "factori_reset2"> (bez internog uređaja za skladištenje) </string>
<string name = "factori_reset3"> Uglavnom je </string>
<string name = "factori_reset4"> jedino čišćenje koje vam je potrebno. </string>
<string name = "factori_resetting"> Resetuj na neuspešno. vredi. ... </string>
<string name = "advanced_vipe_hdr"> Napredno čišćenje </string>
<string name = "advanced_vipe_btn"> Napredno čišćenje </string>
<string name = "vipe_enc_confirm"> Obriši šifrovanje podataka? </string>
<string name = "formatting_data"> Formatiranje podataka ... </string>
<string name = "swipe_format_data"> Povucite da formatirate podatke </string>
<string name = "swipe_format_data_s"> Formatiraj podatke </string>
<string name = "factori_reset_complete"> Reset na fabričke vrednosti </string>
<string name = "sel_part_hdr"> Izaberite sekcije </string>
<string name = "vipe_sel_confirm"> Obriši izabrane sekcije? </string>
<string name = "viping_part"> Čišćenje particija ... </string>
<string name = "vipe_complete"> Čišćenje završeno </string>
<string name = "sel_part_vipe"> Izaberite sekcije za čišćenje: </string>
<string name = "invalid_part_sel"> Nevažeća selekcija particija </string>
<string name = "format_data_hdr"> Formatiraj podatke </string>
<string name = "format_data_btn"> Formatiraj podatke </string>
<string name = "format_data_ptr1"> Formatiranje podataka će izbrisati sve programe, </string>
<string name = "format_data_ptr2"> rezervne kopije, slike, video zapisi, mediji i </string>
<string name = "format_data_ptr3"> uklanja šifrovanje na uređaju interne memorije. </string>
<string name = "format_data_adopted"> Uključuje stečeni memorijski uređaj </string>
<string name = "format_data_lcp1"> Podaci o formatiranju će izbrisati sve vaše programe, rezervne kopije, slike, video zapise, medije i </string>
<string name = "format_data_lcp2"> uklonite enkripciju na uređaju interne memorije. </string>
<string name = "format_data_vtc1"> Formatiranje podataka će izbrisati sve programe, </string>
<string name = "format_data_vtc2"> backup i mediji. Ovo se ne može poništiti. </string>
<string name = "format_data_undo"> Ovo se ne može poništiti. </string>
<string name = "format_data_complete"> Oblikovani podaci </string>
<string name = "ies_continue"> Unesite "da" da biste nastavili. Za povratak pritisnite Nazad. </string>
<string name = "part_opt_hdr"> Opcije particije za:% tv_partition_name% </string>
<string name = "sel_act_hdr"> Izaberite akciju </string>
<string name = "file_sis_opt"> Opcije sistema datoteka </string>
<string name = "partition"> Odeljak:% tv_partition_name% </string>
<string name = "part_mount_point"> Tačka veze:% tv_partition_mount_point% </string>
<string name = "part_curr_fs"> Sistem datoteka:% tv_partition_file_sistem% </string>
<string name = "part_present_ies"> Present: ies </string>
<string name = "part_present_no"> Present: no </string>
<string name = "part_removable_ies"> Removable: ies </string>
<string name = "part_removable_no"> Removable: no </string>
<string name = "part_size"> Veličina:% tv_partition_size% MB </string>
<string name = "part_used"> Koristi se:% tv_partition_used% MB </string>
<string name = "part_free"> Unassigned:% tv_partition_free% MB </string>
<string name = "part_backup_size"> Veličina rezervne kopije:% tv_partition_backup_size% MB </string>
<string name = "resize_btn"> Promenite veličinu dat. sistem </string>
<string name = "resize_btn_s"> Spr. </string>
<string name = "resize_confirm"> Promeni veličinu% tv_partition_name%? </string>
<string name = "resizing"> Resize ... </string>
<string name = "resize_complete"> Promena veličine dovršene </string>
<string name = "swipe_resize"> Povucite za spr. size </string>
<string name = "swipe_resize_s"> Spr. size </string>
<string name = "repair_btn"> Ispravi sistem datoteka </string>
<string name = "repair_btn_s"> Fik </string>
<string name = "repair_confirm"> Popravi% tv_partition_name%? </string>
<string name = "repairing"> Ispravka ... </string>
<string name = "repair_complete"> Ispravka dovršena </string>
<string name = "swipe_repair"> Povucite da popravite </string>
<string name = "swipe_repair_s"> Fik </string>
<string name = "change_fs_btn"> Promeni sistem datoteka </string>
<string name = "change_fs_btn_s"> Promeni </string>
<string name = "change_fs_for_hdr"> Promenite sistem datoteka za:% tv_partition_name% </string>
<string name = "change_fs_for_hdr_s"> Odeljak:% tv_partition_name% & gt; izaberite sistem datoteka </string>
<string name = "change_fs_varn1"> Neki ROM-ovi ili jezgra ne podržavaju sve </string>
<string name = "change_fs_varn2"> sisteme datoteka. Nastavite sa pažnjom! </string>
<string name = "change_fs_confirm"> Promeni% tv_partition_name%? </string>
<string name = "formatiranje"> Formatiranje ... </string>
<string name = "format_complete"> Formatiranje je završeno </string>
<string name = "swipe_change_fs"> Povucite za promenu </string>
<string name = "swipe_change_s"> Promeni </string>
<string name = "back_btn"> Nazad </string>
<string name = "vipe_enc_btn"> Obriši šifrovanje </string>
<string name = "swipe_factori_reset"> Povucite da biste vratili na neuspešno. values </string>
<string name = "repair_change_btn"> Popravi ili promeni sistem datoteka </string>
<string name = "storage_hdr"> Memorijski uređaj:% tv_storage_displai_name% (% tv_storage_free_size% MB) </string>
<string name = "backup_hdr"> Var. copi </string>
<string name = "backup_confirm_hdr"> Potvrdi Backup </string>
<string name = "encription_tab"> CODE </string>
<string name = "enkripcija"> Šifrovanje: </string>
<string name = "name"> Ime: </string>
<string name = "sel_part_backup"> Izaberite sekcije za pravljenje rezervnih kopija: </string>
<string name = "storage"> Pomoć. device: </string>
<string name = "enc_disabled"> onemogućen - postavite omogućenu lozinku </string>
<string name = "enc_enabled"> omogućen </string>
<string name = "enable_backup_comp_chk"> Omogući kompresiju </string>
<string name = "skip_digest_backup_chk" version = "2"> Preskoči Kreiranje Digest Digest-a tokom Backup-a </string>
<string name = "disable_backup_space_chk"> Onemogući provjeru slobodnog prostora </string>
<string name = "refresh_sizes_btn"> Osveži veličine </string>
<string name = "swipe_backup"> Povucite na var. kopiranje </string>
<string name = "append_date_btn"> Priložite datum </string>
<string name = "backup_name_ekists"> Rezervna kopija sa istim imenom već postoji! </string>
<string name = "encript_backup"> Šifriraj Backup? </string>
<string name = "enter_pass"> Unesite lozinku: </string>
<string name = "enter_pass2"> Ponovo unesite lozinku: </string>
<string name = "pass_not_match"> Lozinke se ne podudaraju! </string>
<string name = "particije"> Odeljak: </string>
<string name = "disabled"> Disabled </string>
<string name = "enabled"> Enabled </string>
<string name = "backup_name_hdr"> Podesite ime rezervne kopije </string>
<string name = "progress"> Napredak: </string>
<string name = "backup_complete"> Rezervna kopija završena </string>
<string name = "restore_hdr"> Vrati </string>
<string name = "sel_backup_hdr"> Izaberite backup </string>
<string name = "restore_sel_store_hdr"> Izaberite backup od% tv_storage_displai_name% (% tv_storage_free_size% MB) </string>
<string name = "restore_sel_pack_fs"> Izaberite paket za oporavak: </string>
<string name = "restore_enc_backup_hdr"> Šifrovana rezervna kopija </string>
<string name = "restore_dec_fail"> Lozinka nije uspela, pokušajte ponovo! </string>
<string name = "del_backup_btn"> Izbriši rezervnu kopiju </string>
<string name = "del_backup_confirm"> Izbriši Backup? </string>
<string name = "del_backup_confirm2"> Ovo se ne može poništiti! </string>
<string name = "deleting_backup"> Brisanje rezervne kopije ... </string>
<string name = "backup_deleted"> Brisanje rezervne kopije </string>
<string name = "swipe_delete"> Povucite za brisanje </string>
<string name = "swipe_delete_s"> Izbriši </string>
<string name = "restore_tri_decript"> Šifrovana rezervna kopija - pokušaj šifrovanja </string>
<string name = "restore_tri_decript_s"> Testiranje šifrovanja </string>
<string name = "restore_backup_date"> Napravljena rezervna kopija% tv_restore_file_date% </string>
<string name = "restore_sel_part"> Izaberite sekcije za oporavak: </string>
<string name = "restore_enable_digest_chk" version = "2"> Omogući proveru spreja Digest backups </string>
<string name = "restore_complete"> Vraćanje završeno </string>
<string name = "swipe_restore"> Povucite da biste vratili </string>
<string name = "swipe_restore_s"> Vrati </string>
<string name = "rename_backup_hdr"> Preimenuj Backup </string>
<string name = "rename_backup_confirm"> Preimenuj Backup? </string>
<string name = "rename_backup_confirm2"> Ovo se ne može poništiti! </string>
<string name = "renaming_backup"> Preimenuj rezervnu kopiju ... </string>
<string name = "rename_backup_complete"> Preimenovanje rezervne kopije </string>
<string name = "swipe_to_rename"> Povucite za prefiks </string>
<string name = "swipe_rename"> Preimenuj </string>
<string name = "confirm_hdr"> Potvrdi </string>
<string name = "mount_hdr"> Attach </string>
<string name = "mount_sel_part"> Izaberite sekcije za povezivanje: </string>
<string name = "mount_sis_ro_chk"> Povezuje sekciju samo za čitanje </string>
<string name = "mount_sis_ro_s_chk"> Povežite sistem samo za čitanje </string>
<string name = "decript_data_btn"> Dešifriraj podatke </string>
<string name = "disable_mtp_btn"> Onemogući MTP </string>
<string name = "enable_mtp_btn"> Omogući MTP </string>
<string name = "mount_usb_storage_btn"> Povezuje USB uređaj za skladištenje </string>
<string name = "usb_storage_hdr"> Pomoć. USB uređaj </string>
<string name = "usb_stor_mnt1"> USB uređaj za skladištenje povezan sa </string>
<string name = "usb_stor_mnt2"> Obavezno uklonite uređaj </string>
<string name = "usb_stor_mnt3"> iz kompjutera pre prekida veze! </string>
<string name = "unmount_btn"> Prekini vezu </string>
<string name = "rb_sistem_btn"> Sistem </string>
<string name = "rb_poveroff_btn"> Isključi </string>
<string name = "rb_recoveri_btn"> Oporavak </string>
<string name = "rb_bootloader_btn"> Boot Loader </string>
<string name = "rb_dovnload_btn"> Primi </string>
<string name = "rb_edl_btn"> Edl </string>
<string name = "turning_off"> Isključivanje ... </string>
<string name = "swipe_pover_off"> Povucite da biste isključili </string>
<string name = "swipe_pover_off_s"> Isključi </string>
<string name = "sis_ro_hdr"> Nepromenjena sistemska particija </string>
<string name = "sis_ro_keep"> Zadrži sistem samo za čitanje? </string>
<string name = "sis_rop1"> TWRP može ostaviti sistemsku particiju nepromenjenu </string>
<string name = "sis_rop2"> za lakše službeno ažuriranje. </string>
<string name = "sis_rop3"> TWRP neće moći da spreči fabrički ROM </string>
<string name = "sis_rop4"> zamenjuje TWRP i ne nudi administratorski pristup uređaju. </string>
<string name = "sis_rop5"> Instaliranje zip-a ili izvršavanje ADB zadataka i dalje može biti </string>
<string name = "sis_rop6"> menja sistemsku particiju. </string>
<string name = "sis_rol1"> TWRP može ostaviti sistemsku particiju nepromenjenu radi lakšeg formalnog ažuriranja. </string>
<string name = "sis_rol2"> TWRP neće moći da spreči da TWRP zameni TWRP sa fabričkim ROM-om i neće ponuditi administratorski pristup uređaju. </string>
<string name = "sis_rol3"> Instaliranje zip-a ili izvođenje zadataka ADB i dalje može da promeni sistemsku particiju. </string>
<string name = "sis_ro_never_shov_chk"> Nikada više ne prikazujte ovaj ekran tokom pokretanja </string>
<string name = "sis_ro_keep_ro_btn"> Zadrži samo čitanje </string>
<string name = "swipe_allov_mod"> Povucite da biste dozvolili promene </string>
<string name = "swipe_allov_mod_s"> Dozvoli izmene </string>
<string name = "settings_hdr"> Podešavanja </string>
<string name = "settings_gen_hdr"> General </string>
<string name = "settings_gen_s_hdr"> General </string>
<string name = "settings_gen_btn"> General </string>
<string name = "use_rmrf_chk"> Koristite rm -rf umesto formatiranja </string>
<string name = "use24clock_chk"> Koristite 24-časovni format </string>
<string name = "rev_navbar_chk"> Obrnuta navigacija navigacijske trake </string>
<string name = "simact_chk"> Simulacija akcije za testiranje tema </string>
<string name = "simfail_chk"> Simulacija neuspelih akcija </string>
<string name = "ctr_navbar_rdo"> Okretanje dugmadi redova </string>
<string name = "lft_navbar_rdo"> Levi tasteri za navigaciju na levoj strani </string>
<string name = "rht_navbar_rdo"> Desni navigacioni tasteri </string>
<string name = "restore_defaults_btn"> Vrati podrazumevani </string>
<string name = "settings_tz_btn"> Vremenska zona </string>
<string name = "settings_screen_btn"> Prikaz </string>
<string name = "settings_screen_bright_btn"> Osvetljenost ekrana </string>
<string name = "settings_vibration_btn"> Vibracija </string>
<string name = "settings_language_btn"> Jezik </string>
<string name = "time_zone_hdr"> Vremenska zona </string>
<string name = "sel_tz_list"> Izaberite vremensku zonu: </string>
<string name = "utcm11"> (UTC -11) Samoa, Midvai Islands </string>
<string name = "utcm10"> (UTC -10) Havaji </string>
<string name = "utcm9"> (UTC -9) Aljaska </string>
<string name = "utcm8"> (UTC -8) Američko zapadno vreme </string>
<string name = "utcm7"> (UTC-7) Američko srednjezapadno vreme </string>
<string name = "utcm6"> (UTC-6) Američko centralno vreme </string>
<string name = "utcm5"> (UTC -5) Amerikansko istočno vreme </string>
<string name = "utcm4"> (UTC -4) Atlantsko vreme </string>
<string name = "utcm3"> (UTC -3) Brazilija, Buenos Aires </string>
<string name = "utcm2"> (UTC -2) </string>
<string name = "utcm1"> (UTC -1) Azori, Kabo Verde </string>
<string name = "utc0"> (UTC 0) London, Dablin, Lisabon </string>
<string name = "utcp1"> (UTC +1) Berlin, Brisel, Pariz </string>
<string name = "utcp2"> (UTC +2) Atina, Istanbul, Južna Afrika </string>
<string name = "utcp3"> (UTC +3) Moskva, Bagdad </string>
<string name = "utcp4"> (UTC +4) Abu Dabi, Tbilisi, Muskat </string>
<string name = "utcp5"> (UTC +5) Ekaterinburg, Islamabad </string>
<string name = "utcp6"> (UTC +6) Almati, Daka, Kolombo </string>
<string name = "utcp7"> (UTC +7) Bangkok, Hanoj, Džakarta </string>
<string name = "utcp8"> (UTC +8) Peking, Singapur, Hongkong </string>
<string name = "utcp9"> (UTC +9) Tokijo, Seul, Akutsk </string>
<string name = "utcp10"> (UTC +10) Istočna Australija, Guam </string>
<string name = "utcp11"> (UTC +11) Vladivostok, Solomonska ostrva </string>
<string name = "utcp12"> (UTC +12) Okland, Velington, Fidži </string>
<string name = "sel_tz_offset"> Izaberite kašnjenje (obično 0):%tv_time_zone_guioffset% </string>
<string name = "tz_offset_none"> None </string>
		<string name="tz_offset_0">0</string>
		<string name="tz_offset_15">15</string>
		<string name="tz_offset_30">30</string>
		<string name="tz_offset_45">45</string>
<string name = "use_dst_chk"> Koristite Summer Time (DST) </string>
<string name = "curr_tz"> Trenutna vremenska zona:% tv_time_zone% </string>
<string name = "curr_tz_s"> Trenutna vremenska zona: </string>
<string name = "set_tz_btn"> Postavlja vremensku zonu </string>
<string name = "settings_screen_hdr"> Prikaz </string>
<string name = "settings_screen_timeout_hdr"> Timeout ekrana </string>
<string name = "enable_timeout_chk"> Omogući vremensko ograničenje ekrana </string>
<string name = "screen_to_slider"> Timeout u sekundama: </string>
<string name = "screen_to_slider_s"> Timeout u sekundama: (0 = onemogućeno):% tv_screen_timeout_secs% </string>
<string name = "screen_to_na"> Podešavanje vremenskog ograničenja ekrana nije dostupno </string>
<string name = "screen_bright_slider"> Osvetljenost:% tv_brightness_pct %% </string>
<string name = "screen_bright_na"> Postavka osvetljenosti nije dostupna </string>
<string name = "vibration_hdr"> Vibracija </string>
<string name = "button_vibration_hdr"> Vibracioni tasteri </string>
<string name = "kb_vibration_hdr"> Vibracija tastature </string>
<string name = "act_vibration_hdr"> Akcije vibracije </string>
<string name = "button_vibration"> Vibracioni tasteri: </string>
<string name = "kb_vibration"> Vibracija tastature: </string>
<string name = "act_vibration"> Vibracija: </string>
<string name = "select_language"> Izaberite jezik: </string>
<string name = "sel_lang_btn"> Izaberite jezik </string>
<string name = "set_language_btn"> Podesite jezik </string>
<string name = "advanced_hdr"> Napredno </string>
<string name = "copi_log_confirm"> Kopirajte dnevnik na SD karticu? </string>
<string name = "copiing_log"> Kopirajte dnevnik na SD karticu ... </string>
<string name = "copi_log_complete"> Kopiraj dnevnik završen </string>
<string name = "part_sd_btn"> Podelite SD karticu </string>
		<string name="part_sd_s_btn">Kartica SD</string>
		<string name="file_manager_btn">Upravnik datoteka</string>
		<string name="language_hdr">Jezik</string>
		<string name="terminal_btn">Terminal</string>
<string name = "reload_theme_btn"> Osveži temu </string>
<string name = "dumlock_btn"> HTC Dumlock </string>
<string name = "inject_TWRP_btn"> Umetnite TWRP </string>
<string name = "inject_TWRP_confirm"> Ponovo instaliraj TWRP? </string>
<string name = "injecting_TWRP"> Ponovo instaliraj TWRP ... </string>
<string name = "inject_TWRP_complete"> Umetnite TWRP dovršen </string>
<string name = "swipe_to_confirm"> Povucite za potvrdu </string>
<string name = "part_sd_hdr"> Podelite SD karticu </string>
<string name = "invalid_partsd_sel"> Morate odabrati prenosivi uređaj </string>
<string name = "part_sd_lose"> Izgubićete sve datoteke na SD kartici! </string>
<string name = "part_sd_undo"> Ova akcija se ne može poništiti! </string>
<string name = "part_sd_ekt_sz"> EKST size: </string>
<string name = "part_sd_svap_sz"> Izmeni. size: </string>
<string name = "part_sd_m"> - </string>
<string name = "part_sd_p"> + </string>
<string name = "file_sistem"> Sistem fajlova: </string>
<string name = "swipe_part_sd"> Drag to split </string>
<string name = "swipe_part_sd_s"> Odeljak </string>
<string name = "partitioning_sd"> Distribucija SD kartice ... </string>
<string name = "partitioning_sd2"> Potrebno je nekoliko minuta. </string>
<string name = "part_sd_complete"> Distribucija je završena </string>
<string name = "dumlock_hdr"> HTC Dumlock </string>
<string name = "dumlock_restore_btn"> Vrati originalno pokretanje </string>
<string name = "dumlock_restore_confirm"> Vraća originalni boot print? </string>
<string name = "dumlock_restoring"> Obnavljanje originalnog pokretanja ... </string>
<string name = "dumlock_restore_complete"> Vraćanje originalnog pokretanja dovršeno </string>
<string name = "dumlock_reflash_btn"> Ponovo instalirajte oporavak </string>
<string name = "dumlock_reflash_confirm"> Ponovo instaliraj obnovu u startup? </string>
<string name = "dumlock_reflashing"> Instaliranje obnavljanja za pokretanje ... </string>
<string name = "dumlock_reflash_complete"> Instaliraj za vraćanje u startup </string>
<string name = "dumlock_install_btn"> Instalirajte HTC Dumlock </string>
<string name = "dumlock_install_confirm"> Instalirajte HTC Dumlock u ROM? </string>
<string name = "dumlock_installing"> Instaliranje HTC Dumlock ... </string>
<string name = "dumlock_install_complete"> Instaliranje HTC Dumlock-a završeno </string>
<string name = "swipe_to_unlock"> Povucite da biste otključali </string>
<string name = "swipe_unlock"> Otključaj </string>
<string name = "fm_hdr"> Upravnik datoteka </string>
<string name = "fm_sel_file"> Izaberite fajl ili folder </string>
<string name = "fm_tipe_folder"> Folder </string>
<string name = "fm_tipe_file"> Datoteka </string>
<string name = "fm_choose_act"> Izaberite akciju </string>
<string name = "fm_selected"> Izabrani% tv_fm_tipe%: </string>
<string name = "fm_copi_btn"> Kopiraj </string>
<string name = "fm_copi_file_btn"> Kopiraj fajl </string>
<string name = "fm_copi_folder_btn"> Kopiraj direktorijum </string>
<string name = "fm_copiing"> Kopiraj ... </string>
<string name = "fm_move_btn"> Premesti </string>
<string name = "fm_moving"> Premesti </string>
<string name = "fm_chmod755_btn"> chmod 755 </string>
<string name = "fm_chmod755ing"> chmod 755 </string>
<string name = "fm_chmod_btn"> chmod </string>
<string name = "fm_delete_btn"> Izbriši </string>
<string name = "fm_deleting"> Izbriši ... </string>
<string name = "fm_rename_btn"> Preimenuj </string>
<string name = "fm_rename_file_btn"> Preimenuj fajl </string>
<string name = "fm_rename_folder_btn"> Preimenuj folder </string>
<string name = "fm_renaming"> Preimenuj </string>
<string name = "fm_sel_dest"> Izaberite odredišnu fasciklu </string>
<string name = "fm_sel_curr_folder"> Izaberite trenutni folder </string>
<string name = "fm_rename_hdr"> Preimenuj </string>
<string name = "fm_set_perms_hdr"> Postavite dozvole </string>
<string name = "fm_perms"> Dozvole: </string>
<string name = "fm_complete"> Zadatak za datoteke završene </string>
<string name = "decript_data_hdr"> Dešifriraj podatke </string>
<string name = "decript_data_enter_pass"> Unesite lozinku. </string>
<string name = "decript_data_enter_pattern"> Unesite uzorak. </string>
<string name = "decript_data_triing"> Testiranje kodiranja </string>
<string name = "term_hdr"> Komanda terminala </string>
		<string name="term_s_hdr">Terminal</string>
<string name = "term_kill_btn"> UNIT </string>
<string name = "term_sel_folder_hdr"> Pregledajte početni direktorijum </string>
<string name = "adb_sideload_hdr"> Side-Load ADB </string>
<string name = "sideload_vipe_dalvik_chk"> Očisti Dalvik keš </string>
<string name = "sideload_vipe_cache_chk"> Obrišite prefiks. </string>
<string name = "swipe_to_sideload"> Povucite da biste započeli sideloading </string>
<string name = "swipe_sideload"> Start </string>
<string name = "sideload_confirm"> Side-Load ADB </string>
<string name = "sideload_usage"> Upotreba: adb sideload filename.zip </string>
<string name = "sideload_complete"> ADB-a sa bočnim učitavanjem dovršen </string>
<string name = "reboot_hdr"> Pon. pokrenite </string>
<string name = "install_cancel"> Ne instalirajte </string>
<string name = "sel_storage_list"> Izaberite memorijski uređaj </string>
<string name = "ok_btn"> OK </string>
<string name = "no_kernel_selinux"> Kernel nema podršku za čitanje selinux sadržaja. </string>
<string name = "full_selinux"> Postoji potpuna podrška za selinux. </string>
<string name = "no_selinux"> Ne postoji podrška za selinux (nedostaje libselinux). </string>
<string name = "mtp_enabled"> MTP omogućen </string>
<string name = "mtp_crash"> MTP se srušio, MTP neće početi prilikom pokretanja. </string>
<string name = "decript_success"> Uspešno šifrovana sa podrazumevanom lozinkom. </string>
<string name = "unable_to_decript"> Otključavanje sa podrazumevanom lozinkom nije moguće. Možda ćete morati da formatirate informacije. </string>
<string name = "generating_digest1" version = "2"> Generisanje Digest Digest </string>
<string name = "generating_digest2" version = "2"> * Kreiranje probavnog spreja ... </string>
<string name = "digest_created" version = "2"> * Digest Digest kreiran. </string>
<string name = "digest_error" version = "2"> * Digest digest! </string>
<string name = "digest_compute_error" version = "2"> * Digest Digest. </string>
<string name = "current_date"> (trenutni datum) </string>
<string name = "auto_generate"> (automatski generisan) </string>
<string name = "unable_to_locate_partition"> Ne može da pronađe odeljak {1} za izračunavanje rezervnih kopija.
<string name = "no_partition_selected"> Nema izabranih sekcija rezervne kopije. </string>
<string name = "total_partitions_backup"> * Ukupan broj sigurnosnih sekcija: {1} </string>
<string name = "total_backup_size"> * Ukupna veličina svih podataka: {1} MB </string>
<string name = "available_space"> * Neiskorišćeni prostor: {1} MB </string>
<string name = "unable_locate_storage"> Ne može da nađe memorijski uređaj. </string>
<string name = "no_space"> Nema dovoljno prostora na memorijskom uređaju. </string>
<string name = "backup_started"> [VAR. KOPIRANJE JE POČELO] </string>
<string name = "backup_folder"> * Backup folder: {1} </string>
<string name = "fail_backup_folder"> Kreiranje direktorijuma rezervne kopije nije uspelo. </string>
<string name = "avg_backup_fs"> Prosečna brzina kopiranja za sisteme datoteka: {1} MB / s </string>
<string name = "avg_backup_img"> Prosečna brzina rezervne kopije za diskove: {1} MB / s </string>
<string name = "total_backed_size"> [OBEZBEĐENO KOPIRANO UKUPNO {1} MB] </string>
<string name = "backup_completed"> [OBEZBEĐENO KOPIRANJE ZAVRŠENO ZA {1} S] </string>
<string name = "restore_started"> [OPORAVAK STARTOVAN] </string>
<string name = "restore_folder"> Fascikla za oporavak: {1} </string>
<string name = "verifiing_digest" version = "2"> Digest provera </string>
<string name = "skip_digest" version = "2"> Preskačem testiranje Digesta po korisničkoj želji. </string>
<string name = "calc_restore"> Izračunavanje detalja oporavka ... </string>
<string name = "restore_read_onli"> {1} se ne može obnoviti - samo je za čitanje. </string>
<string name = "restore_unable_locate"> Odjeljak {1} za oporavak se ne može pronaći.
<string name = "no_part_restore"> Nema izabranih particija za oporavak. </string>
<string name = "restore_part_count"> Vrati {1} sekcije ... </string>
<string name = "total_restore_size"> Ukupna veličina oporavka je {1} MB </string>
<string name = "updating_sistem_details"> Ažuriranje detalja sistema </string>
<string name = "restore_completed"> [UPDATE FINAL IN {1} S] </string>
<string name = "error_opening_strerr"> Otvaranje greške: {1} ({2}) </string>
<string name = "unable_locate_part_backup_name"> Ne mogu da pronađem odeljak po imenu rezervne kopije: {1} </string>
<string name = "unable_find_part_path"> Sekcija puta '{1}' nije pronađena </string>
<string name = "update_part_details"> Ažuriranje detalja sekcije ... </string>
<string name = "update_part_details_done"> ... gotov </string>
<string name = "viping_dalvik"> Brisanje foldera Dalvik keša ... </string>
<string name = "cleaned"> Obriši: {1} ... </string>
<string name = "dalvik_done"> - Brisanje popunjenih fascikli Dalvika u kešu! </string>
<string name = "no_andsec"> Sigurni delovi Android-a nisu pronađeni. </string>
<string name = "unable_to_locate"> {1} nije moguće pronaći. </string>
<string name = "viping_datamedia"> Čišćenje unutrašnjeg uređaja za skladištenje - / data / media ... </string>
<string name = "unable_to_mount"> {1} ne može da se poveže. </string>
<string name = "unable_to_mount_internal"> Interni uređaj za skladištenje ne može biti povezan </string>
<string name = "unable_to_mount_storage"> Ne može da poveže memorijski uređaj </string>
<string name = "fail_decript"> Dešifrovanje podataka nije uspelo. </string>
<string name = "no_cripto_support"> Podrška za šifrovanje nije ugrađena u ovu verziju. </string>
<string name = "decript_success_dev"> Podaci su uspešno dešifrovani, novi blok uređaj: {1} </string>
<string name = "done"> Gotovo. </string>
<string name = "start_partition_sd"> Distribucija SD kartice ... </string>
<string name = "partition_sd_locate"> Uređaj za distribuciju nije pronađen. </string>
<string name = "ekt_svap_size"> Veličina EKST + je veća od veličine SD kartice. </string>
<string name = "remove_part_table"> Uklanjanje tabele particija ... </string>
<string name = "unable_rm_part"> Tabela particija se ne može ukloniti. </string>
<string name = "create_part"> Kreiranje sekcije {1} ... </string>
<string name = "unable_to_create_part"> Sekcija {1} ne može biti kreirana. </string>
<string name = "format_sdekt_as"> Formatiranje SD-EKST kao {1} ... </string>
<string name = "part_complete"> Distribucija je završena. </string>
<string name = "unable_to_open"> {1} ne može se otvoriti. </string>
<string name = "mtp_alreadi_enabled"> MTP je već omogućen </string>
<string name = "mtp_fail"> Omogućavanje MTP-a </string>
<string name = "no_mtp"> MTP podrška nije uključena </string>
<string name = "image_flash_start"> [POČELA JE UGRADNJA CRTEŽE] </string>
<string name = "img_to_flash"> Popravi za instalaciju: {1} </string>
<string name = "flash_unable_locate"> Odeljak '{1}' ne može se naći za instalaciju. </string>
<string name = "no_part_flash"> Nema izabranih sekcija za instalaciju. </string>
<string name = "too_mani_flash"> Odabrano previše instalacionih delova. </string>
<string name = "invalid_flash"> Navedena je neispravna sekcija instalacije. </string>
<string name = "flash_done"> [ZAVRŠENO FLEŠOVANJE]] </string>
		<string name="wiping">Čiščenje {1}</string>
<string name = "repair_not_ekist"> {1} ne postoji! Ne može se popraviti! </string>
<string name = "repairing_using"> Ispravka {1} s / z {2} ... </string>
<string name = "unable_repair"> Popravka {1} nije moguća. </string>
<string name = "mount_data_footer"> / podaci se ne mogu montirati i prostor za enkripciju nije moguće pronaći. </string>
<string name = "create_folder_strerr"> Fascikle {1} nije moguće kreirati ({2}). </string>
<string name = "fail_mount"> Veza '{1}' failed ({2}) </string>
<string name = "fail_unmount"> Prekini vezu {1} ​​\ t
<string name = "cannot_resize"> Veličine {1} se ne mogu promeniti. </string>
<string name = "repair_resize"> Ispravi {1} pre promene veličine. </string>
<string name = "unable_resize"> Veličine {1} se ne mogu promeniti. </string>
<string name = "no_digest_found" version = "2"> Datoteka sa sažetkom nije pronađena za {1}. Molimo Vas da uklonite "Omogući pregled" da potvrdite Digestov izbor. </string>
<string name = "digest_fail_match" version = "2"> Digest Digest Digg to {1} nije uspio. </string>
<string name = "digest_matched" version = "2"> Digest se podudara za '{1}'. </string>
<string name = "fail_decript_tar"> Otključavanje TAR-a {1} \ t
<string name = "format_data_msg"> Možda ćete morati ponovo pokrenuti oporavak za ponovnu upotrebu / podatke. </string>
<string name = "format_data_err"> Nije moguće formatirati enkripciju. </string>
<string name = "formatting_using"> Formatiranje {1} s / z {2} ... </string>
<string name = "unable_to_vipe"> Čišćenje {1} nije moguće. </string>
<string name = "cannot_vipe"> Sekcija {1} se ne može obrisati. </string>
<string name = "remove_all"> Uklanjanje svih datoteka u {1} ​​</string>
<string name = "viping_data"> Čišćenje podataka bez čišćenja / podataka / medija ... </string>
<string name = "backing_up"> Sigurnosna kopija {1} ... </string>
<string name = "backing"> Backup </string>
<string name = "backup_size"> Veličina rezervne kopije za {1} je 0 B. </string>
<string name = "datamedia_fs_restore"> UPOZORENJE: ova rezervna kopija / podaci su kreirani pomoću sistema datoteka {1}! Rezervna kopija se možda neće pokrenuti ako se ne vratite na {1}. </string>
<string name = "vraćanje"> Vraćanje {1} ... </string>
<string name = "restoring_hdr"> Vrati </string>
<string name = "recreate_folder_err"> Mape {1} se ne mogu ponovo kreirati. </string>
<string name = "img_size_err"> Veličina štampanja je veća od ciljnog uređaja </string>
<string name = "flashing"> Instalacija {1} ... </string>
<string name = "backup_folder_set"> Mapa za rezervne kopije postavljena na \ _ {1} \ _ </string> \ t
<string name = "locate_backup_err"> Sigurnosna kopija {1} \ t
<string name = "set_restore_opt"> Podešavanje opcija za pravljenje rezervne kopije: {1}: </string>
<string name = "digest_check_skip" version = "2"> Preskoči. checking raz. Digest je na </string>
<string name = "ors_encript_restore_err"> OpenRecoveryScript se ne može koristiti za vraćanje šifrovanih rezervnih kopija. </string>
<string name = "mounting"> Attach </string>
<string name = "unmounting"> Otključaj </string>
<string name = "mounted"> {1} povezan sa </string>
<string name = "unmounted"> "{1}" odspojen </string>
<string name = "postavljanje"> Podešavanje \ _ {1} na {2} </string>
<string name = "setting_empti"> Podešavanje \ _ {1} \ _ da se isprazni </string>
<string name = "making_dir1"> Kreiranje foldera </string>
<string name = "making_dir2"> Kreiranje fascikle: {1} </string>
<string name = "running_command"> Pokretanje komande </string>
<string name = "sideload"> ADB </string>
<string name = "start_sideload"> Pokretanje ADB Sideload-a ... </string>
<string name = "need_nev_adb"> Potreban vam je ADB 1.0.32 ili noviji za ovaj uređaj </string>
<string name = "no_pvd"> Lozinka nije navedena. </string>
<string name = "done_ors"> Obrada datoteke skripte je završena </string>
<string name = "injectTWRP"> Ubacivanje TWRP-a u bootable print ... </string>
<string name = "zip_err"> Greška pri instalaciji ZIP-a {1} </string>
<string name = "installing_zip"> Instaliranje ZIP-a {1} </string>
<string name = "select_backup_opt"> Podešavanje opcija backupa: </string>
<string name = "compression_on"> Kompresija je uključena </string>
<string name = "digest_off" version = "2"> Kreiranje Digesta je isključeno </string>
<string name = "backup_fail"> Bekap nije uspeo </string>
<string name = "backup_clean"> Rezervna kopija nije uspela. Očistite fasciklu sa rezervnim kopijama. </string>
<string name = "running_recoveri_commands"> Izvođenje naredbi za oporavak </string>
<string name = "recoveri_commands_complete"> Vraćene komande vraćanja </string>
<string name = "running_ors"> Implementacija OpenRecoveriScripta </string>
<string name = "ors_complete"> OpenRecoveriScript je dovršen </string>
<string name = "no_updater_binari"> Nije moguće pronaći {1} u ZIP datoteci </string> 
<string name = "check_for_digest" version = "2"> Digest File Digest ... </string>
<string name = "fail_sismap"> Mapiranje datoteka {1} je neispravno </string>
<string name = "verifi_zip_sig"> Proveri ZIP potpis </string>
<string name = "verifi_zip_fail"> Provera ZIP potpisa nije uspela! </string>
<string name = "verifi_zip_done"> Verifikacija ZIP potpisa je uspela! </string>
<string name = "zip_corrupt"> ZIP fajl je oštećen! </string>
<string name = "no_digest" version = "2"> Dump Digest provera: Digest datoteka nije pronađena </string>
<string name = "digest_fail" version = "2"> Digest ne odgovara </string>
<string name = "digest_match" version = "2"> Digest match </string>
<string name = "pid_signal"> {1} zadatak je završio signalom: {2} </string>
<string name = "pid_error"> {1} zadatak je završio greškom: {2} </string>
<string name = "install_dumlock"> Instaliranje HTC Dumlock-a na sistem ... </string>
<string name = "dumlock_restore"> Dumlock originalno pokretanje ... </string>
<string name = "dumlock_reflash"> Ponovo instalirajte Dumlock da biste pokrenuli ... </string>
<string name = "run_script"> Pokretanje skripte {1} ... </string>
<string name = "rename_stock"> Fabrički /sistem fajl je preimenovan da bi sprečio da fabrički ROM zameni TWRP. </string>
<string name = "split_backup"> Podela rezervne kopije u više arhiva ... </string>
<string name = "backup_error"> Greška pri kreiranju rezervne kopije. </string>
<string name = "restore_error"> Greška tokom procesa oporavka. </string>
<string name = "split_thread"> Podelite ID i {1} u arhivu {2} </string>
<string name = "file_progress">% ll od% ll fajlova,% i %% </string>
<string name = "size_progress">% llu MB od% llu MB,% i %% </string>
<string name = "decript_cmd"> Pokušajte da kodirate particiju podataka preko komandne linije. </string>
<string name = "base_pkg_err"> Učitavanje osnovnih paketa nije uspelo. </string>
<string name = "simulacija"> Simulacija akcija ... </string>
<string name = "backup_cancel"> Rezervna kopija je otkazana </string>
<string name = "config_TWRP"> Podešavanje TWRP ... </string>
<string name = "config_TWRP_err"> TWRP ne može biti konfigurisan sa ovim kernelom. </string>
<string name = "copi_log"> Dnevnik oporavka kopiran u {1}. </string>
<string name = "mak_kueue"> Maksimalna veličina ZIP upita dostigla </string>
<string name = "min_kueue"> Minimalna veličina ZIP upita dostignuta! </string>
<string name = "screenshot_saved"> Snimka je sačuvana u {1} ​​</string>
<string name = "screenshot_err"> Snimanje slike na ekranu nije uspjelo! </string>
<string name = "zip_vipe_cache"> Jedan ili više ZIP-ova zahtevaju brisanje keša - čišćenje. </string>
<string name = "and_sec_vipe_err"> Ne može očistiti Android Secure Partition </string>
<string name = "dalvik_vipe_err"> Dalvikovo čišćenje nije uspelo // </string>
<string name = "auto_gen"> (automatski generisan) </string>
<string name = "curr_date"> (trenutni datum) </string>
<string name = "backup_name_len"> Ime rezervne kopije je predugo. </string>
<string name = "backup_name_invalid"> Ime rezervne kopije '{1}' sadrži nevažeći znak: {1} </string>
<string name = "no_real_sdcard"> Ovaj uređaj nema važeću SD karticu! </string>
<string name = "cancel_sideload"> Prekini Sideload ADB ... </string>
<string name = "change_fs_err"> Greška pri promeni fajl-sistema. </string>
<string name = "theme_ver_err"> Prilagođena tema ne odgovara TWRP verziji. Koristiće se fabrička tema. </string>
	</resources>
</language>
